prowl/__init__.py
prowl/cli.py
prowl/examples/__init__.py
prowl/examples/aggsummary.py
prowl/examples/codeit.py
prowl/examples/image.py
prowl/examples/knowledge.py
prowl/examples/monster_gen.py
prowl/examples/ragtot.py
prowl/examples/self_improve.py
prowl/examples/self_write.py
prowl/examples/state.py
prowl/examples/streaming.py
prowl/examples/todo.py
prowl/lib/__init__.py
prowl/lib/error.py
prowl/lib/prowl.py
prowl/lib/stack.py
prowl/lib/tool.py
prowl/lib/vllm.py
prowl/tools/__init__.py
prowl/tools/collect/__init__.py
prowl/tools/collect/tool.py
prowl/tools/comfy/__init__.py
prowl/tools/comfy/comfyutil.py
prowl/tools/comfy/tool.py
prowl/tools/concat/__init__.py
prowl/tools/concat/tool.py
prowl/tools/each/__init__.py
prowl/tools/each/tool.py
prowl/tools/file/__init__.py
prowl/tools/file/tool.py
prowl/tools/include/__init__.py
prowl/tools/include/tool.py
prowl/tools/list/__init__.py
prowl/tools/list/tool.py
prowl/tools/navigate/__init__.py
prowl/tools/navigate/tool.py
prowl/tools/out/__init__.py
prowl/tools/out/tool.py
prowl/tools/prowl/__init__.py
prowl/tools/prowl/tool.py
prowl/tools/recall/__init__.py
prowl/tools/recall/tool.py
prowl/tools/script/__init__.py
prowl/tools/script/tool.py
prowl/tools/search/__init__.py
prowl/tools/search/tool.py
prowl/tools/time/__init__.py
prowl/tools/time/tool.py
prowl/util/__init__.py
prowl/util/vardump.py
prompt_owl-0.1.17.dist-info/LICENSE
prompt_owl-0.1.17.dist-info/METADATA
prompt_owl-0.1.17.dist-info/WHEEL
prompt_owl-0.1.17.dist-info/entry_points.txt
prompt_owl-0.1.17.dist-info/top_level.txt
prompt_owl-0.1.17.dist-info/RECORD
