Metadata-Version: 2.1
Name: prompt-owl
Version: 0.1.17
Summary: A Declarative Prompting Language for LLMs
Home-page: https://github.com/lks-ai/prowl
Author: LoreKeeper Ltd
Author-email: nathaniel@lorekeeper.co.uk
License: MIT
Platform: UNKNOWN
Classifier: Programming Language :: Python :: 3
Classifier: License :: OSI Approved :: MIT License
Classifier: Operating System :: OS Independent
Requires-Python: >=3.9
License-File: LICENSE
Requires-Dist: aiohttp (>=3.9.1)
Requires-Dist: requests (>=2.31.0)
